sockjs_tornado_meiqia-2016.12.30-py2.7-nspkg.pth
sockjs/tornado/__init__.py
sockjs/tornado/basehandler.py
sockjs/tornado/conn.py
sockjs/tornado/migrate.py
sockjs/tornado/periodic.py
sockjs/tornado/proto.py
sockjs/tornado/router.py
sockjs/tornado/session.py
sockjs/tornado/sessioncontainer.py
sockjs/tornado/static.py
sockjs/tornado/stats.py
sockjs/tornado/util.py
sockjs/tornado/websocket.py
sockjs/tornado/transports/__init__.py
sockjs/tornado/transports/base.py
sockjs/tornado/transports/eventsource.py
sockjs/tornado/transports/htmlfile.py
sockjs/tornado/transports/jsonp.py
sockjs/tornado/transports/pollingbase.py
sockjs/tornado/transports/rawwebsocket.py
sockjs/tornado/transports/streamingbase.py
sockjs/tornado/transports/websocket.py
sockjs/tornado/transports/xhr.py
sockjs/tornado/transports/xhrstreaming.py
sockjs_tornado_meiqia-2016.12.30.dist-info/DESCRIPTION.rst
sockjs_tornado_meiqia-2016.12.30.dist-info/METADATA
sockjs_tornado_meiqia-2016.12.30.dist-info/RECORD
sockjs_tornado_meiqia-2016.12.30.dist-info/WHEEL
sockjs_tornado_meiqia-2016.12.30.dist-info/metadata.json
sockjs_tornado_meiqia-2016.12.30.dist-info/namespace_packages.txt
sockjs_tornado_meiqia-2016.12.30.dist-info/top_level.txt
