Metadata-Version: 2.0
Name: sockjs-tornado-meiqia
Version: 2016.12.30
Summary: SockJS python server implementation on top of Tornado framework
Home-page: http://github.com/mrjoes/sockjs-tornado/
Author: Serge S. Koval
Author-email: serge.koval@gmail.com
License: Copyright (C) 2011 Serge S. Koval
Requires-Dist: tornado (>=2.1.1)
